torrent_models-0.3.4.dist-info/METADATA
torrent_models-0.3.4.dist-info/WHEEL
torrent_models-0.3.4.dist-info/entry_points.txt
torrent_models-0.3.4.dist-info/licenses/LICENSE
torrent_models/__init__.py
torrent_models/base.py
torrent_models/cli/__init__.py
torrent_models/cli/main.py
torrent_models/compat.py
torrent_models/const.py
torrent_models/create.py
torrent_models/hashing/__init__.py
torrent_models/hashing/base.py
torrent_models/hashing/hybrid.py
torrent_models/hashing/v1.py
torrent_models/hashing/v2.py
torrent_models/info.py
torrent_models/libtorrent.py
torrent_models/testing/__init__.py
torrent_models/testing/fabricators.py
torrent_models/torrent.py
torrent_models/types/__init__.py
torrent_models/types/common.py
torrent_models/types/serdes.py
torrent_models/types/v1.py
torrent_models/types/v2.py
torrent_models/types/validation.py
torrent_models-0.3.4.dist-info/RECORD
