Metadata-Version: 2.1
Name: torrent-models
Version: 0.3.4
Summary: .torrent file parsing and creation with pydantic
Keywords: bittorrent,torrent,pydantic
Author-Email: sneakers-the-rat <sneakers-the-rat@protonmail.com>
License: EUPL-1.2
Classifier: Framework :: Pydantic
Classifier: Framework :: Pydantic :: 2
Classifier: Programming Language :: Python :: 3
Classifier: Programming Language :: Python :: 3.11
Classifier: Programming Language :: Python :: 3.12
Classifier: Programming Language :: Python :: 3.13
Classifier: Typing :: Typed
Project-URL: repository, https://github.com/p2p-ld/torrent-models
Requires-Python: >=3.11
Requires-Dist: pydantic>=2.10.6
Requires-Dist: bencode-rs>=0.0.7
Requires-Dist: tqdm>=4.67.1
Requires-Dist: typing-extensions>=4.13.0; python_version < "3.12"
Requires-Dist: rich>=14.0.0
Requires-Dist: humanize>=4.12.2
Provides-Extra: cli
Requires-Dist: click>=8.1.8; extra == "cli"
Provides-Extra: libtorrent
Requires-Dist: libtorrent>=2.0.11; extra == "libtorrent"
Provides-Extra: mypy
Requires-Dist: torrent-models[cli]; extra == "mypy"
Requires-Dist: types-tqdm>=4.67.0.20250417; extra == "mypy"
Provides-Extra: tests
Requires-Dist: torrent-models[cli,libtorrent]; extra == "tests"
Requires-Dist: pytest>=8.3.5; extra == "tests"
Requires-Dist: pytest-cov>=6.0.0; extra == "tests"
Requires-Dist: torf>=4.3.0; extra == "tests"
Requires-Dist: pytest-profiling>=1.8.1; extra == "tests"
Provides-Extra: benchmark
Requires-Dist: torrent-models[tests]; extra == "benchmark"
Requires-Dist: pytest-codspeed>=3.2.0; extra == "benchmark"
Provides-Extra: dev
Requires-Dist: torrent-models[mypy,tests]; extra == "dev"
Requires-Dist: ruff>=0.11.2; extra == "dev"
Requires-Dist: black>=25.1.0; extra == "dev"
Requires-Dist: mypy>=1.15.0; extra == "dev"
Requires-Dist: types-tqdm>=4.67.0.20250417; extra == "dev"
Requires-Dist: sphinx-autobuild>=2024.10.3; extra == "dev"
Provides-Extra: docs
Requires-Dist: torrent-models[cli]; extra == "docs"
Requires-Dist: sphinx>=8.2.3; extra == "docs"
Requires-Dist: furo>=2024.8.6; extra == "docs"
Requires-Dist: myst-parser>=4.0.1; extra == "docs"
Requires-Dist: autodoc-pydantic>=2.2.0; extra == "docs"
Requires-Dist: sphinx-design>=0.6.1; extra == "docs"
Requires-Dist: sphinxcontrib-mermaid>=1.0.0; extra == "docs"
Requires-Dist: myst-nb>=1.2.0; extra == "docs"
Requires-Dist: rich>=14.0.0; extra == "docs"
Requires-Dist: sphinx-click>=6.0.0; extra == "docs"
